AudioConverter/__init__.py
AudioConverter/converter.py
AudioConverter-1.0.0.dist-info/LICENSE
AudioConverter-1.0.0.dist-info/METADATA
AudioConverter-1.0.0.dist-info/WHEEL
AudioConverter-1.0.0.dist-info/entry_points.txt
AudioConverter-1.0.0.dist-info/top_level.txt
AudioConverter-1.0.0.dist-info/RECORD
