Metadata-Version: 2.1
Name: AudioConverter
Version: 1.0.0
Summary: Audio Converter CLI
Author: lamdav
Author-email: david.lam@lamdav.com
License: MIT
Project-URL: Bug Reports, https://github.com/lamdaV/AudioConverter/issues
Project-URL: Source, https://github.com/lamdaV/AudioConverter
Keywords: audioconverter audio converter CLI
Classifier: Development Status :: 4 - Beta
Classifier: Environment :: Console
Classifier: Intended Audience :: End Users/Desktop
Classifier: License :: OSI Approved :: MIT License
Classifier: Operating System :: OS Independent
Classifier: Programming Language :: Python :: 3.6
Classifier: Programming Language :: Python :: 3.7
Classifier: Programming Language :: Python :: 3.8
Classifier: Programming Language :: Python :: 3.9
Classifier: Topic :: Multimedia :: Sound/Audio :: Conversion
Classifier: Topic :: Utilities
Requires-Python: >=3.6
License-File: LICENSE
Requires-Dist: click (<8.0.0,>=7.1.2)
Requires-Dist: colorama (<1.0.0,>=0.4.3)
Requires-Dist: pydub (<1.0.0,>=0.24.1)
Provides-Extra: dev
Requires-Dist: black (>=20.8b1) ; extra == 'dev'
Requires-Dist: isort (>=5.6.1) ; extra == 'dev'
Requires-Dist: pur (>=5.3.0) ; extra == 'dev'
